<t:tests xmlns:t="urn:zimbraTestHarness">


<t:property name="test_acct.server" value="NOT_DEFINED"/>
<t:property name="test_acct1.server" value="NOT_DEFINED"/>
<t:property name="test_acct2.server" value="NOT_DEFINED"/>
<t:property name="test_acct3.server" value="NOT_DEFINED"/>
<t:property name="test_acct4.server" value="NOT_DEFINED"/>
<t:property name="test_acct5.server" value="NOT_DEFINED"/>
<t:property name="test_acct6.server" value="NOT_DEFINED"/>
<t:property name="test_acct7.server" value="NOT_DEFINED"/>
<t:property name="test_acct8.server" value="NOT_DEFINED"/>
<t:property name="test_acct9.server" value="NOT_DEFINED"/>
<t:property name="test_acct10.server" value="NOT_DEFINED"/>
<t:property name="test_acct11.server" value="NOT_DEFINED"/>
<t:property name="test_acct12.server" value="NOT_DEFINED"/>

<!-- ALL THE TEST CASES ARE USING AUTH-TOKEN OF NORMAL USER WHO HAS ADMIN RIGHTS  -->

<t:property name="test_account.name" value="test.${TIME}.${COUNTER}@${defaultdomain.name}"/>
<t:property name="test_account.password" value="${defaultpassword.value}"/>


<!-- password age Values:  zimbraPasswordMaxAge:default, zimbraPasswordMinAge:7 zimbraPasswordModifiedTime=-3d-->
<t:property name="test_account1.name" value="test.${TIME}.${COUNTER}@${defaultdomain.name}"/>
<t:property name="test_account1.password" value="test123"/>
<t:property name="test_account1.tmp_password" value="bogus123"/>

<!-- password age Values:  zimbraPasswordMaxAge:default, zimbraPasswordMinAge:7 zimbraPasswordModifiedTime=-10d-->
<t:property name="test_account2.name" value="test.${TIME}.${COUNTER}@${defaultdomain.name}"/>
<t:property name="test_account2.password" value="test123"/>
<t:property name="test_account2.tmp_password" value="bogus123"/>

<!-- password age Values:  zimbraPasswordMaxAge:default, zimbraPasswordMinAge:7 zimbraPasswordModifiedTime=-10d-->
<t:property name="test_account3.name" value="test.${TIME}.${COUNTER}@${defaultdomain.name}"/>
<t:property name="test_account3.password" value="test123"/>
<t:property name="test_account3.tmp_password" value="bogus123"/>

<!-- password age Values:  zimbraPasswordMaxAge:60, zimbraPasswordMinAge:7 zimbraPasswordModifiedTime=-61d-->
<!-- Bug #366 -->
<t:property name="test_account4.name" value="test.${TIME}.${COUNTER}@${defaultdomain.name}"/>
<t:property name="test_account4.password" value="test123"/>
<t:property name="test_account4.tmp_password" value="bogus123"/>

<!-- password age Values:  zimbraPasswordMaxAge:60, zimbraPasswordMinAge:0 zimbraPasswordModifiedTime=-no change- -->
<t:property name="test_account5.name" value="test.${TIME}.${COUNTER}@${defaultdomain.name}"/>
<t:property name="test_account5.password" value="test123"/>
<t:property name="test_account5.tmp_password" value="bogus123"/>

<!-- password age Values:  zimbraPasswordMaxAge:0, zimbraPasswordMinAge:7 zimbraPasswordModifiedTime=-1915d -->
<t:property name="test_account6.name" value="test.${TIME}.${COUNTER}@${defaultdomain.name}"/>
<t:property name="test_account6.password" value="test123"/>
<t:property name="test_account6.tmp_password" value="bogus123"/>

<!-- password age Values:  zimbraPasswordMaxAge:0, zimbraPasswordMinAge:1 zimbraPasswordModifiedTime=-23h59m59s -->
<t:property name="test_account7.name" value="test.${TIME}.${COUNTER}@${defaultdomain.name}"/>
<t:property name="test_account7.password" value="test123"/>
<t:property name="test_account7.tmp_password" value="bogus123"/>

<!-- password age Values:  zimbraPasswordMaxAge:0, zimbraPasswordMinAge:1 zimbraPasswordModifiedTime=-24h1s -->
<t:property name="test_account8.name" value="test.${TIME}.${COUNTER}@${defaultdomain.name}"/>
<t:property name="test_account8.password" value="test123"/>
<t:property name="test_account8.tmp_password" value="bogus123"/>

<!-- password age Values:  zimbraPasswordMaxAge:1, zimbraPasswordMinAge:0 zimbraPasswordModifiedTime=-23h59m59s -->
<t:property name="test_account9.name" value="test.${TIME}.${COUNTER}@${defaultdomain.name}"/>
<t:property name="test_account9.password" value="test123"/>
<t:property name="test_account9.tmp_password" value="bogus123"/>

<!-- password age Values:  zimbraPasswordMaxAge:1, zimbraPasswordMinAge:0 zimbraPasswordModifiedTime=-24h1s -->
<t:property name="test_account10.name" value="test.${TIME}.${COUNTER}@${defaultdomain.name}"/>
<t:property name="test_account10.password" value="test123"/>
<t:property name="test_account10.tmp_password" value="bogus123"/>

<!-- password age Values:  zimbraPasswordMaxAge:365, zimbraPasswordMinAge:7 zimbraPasswordModifiedTime=-364d -->
<t:property name="test_account11.name" value="test.${TIME}.${COUNTER}@${defaultdomain.name}"/>
<t:property name="test_account11.password" value="test123"/>
<t:property name="test_account11.tmp_password" value="bogus123"/>

<!-- password age Values:  zimbraPasswordMaxAge:365, zimbraPasswordMinAge:7 zimbraPasswordModifiedTime=-366d -->
<t:property name="test_account12.name" value="test.${TIME}.${COUNTER}@${defaultdomain.name}"/>
<t:property name="test_account12.password" value="test123"/>
<t:property name="test_account12.tmp_password" value="bogus123"/>

<t:property name="server.zimbraAdmin" value="${zimbraServer.name}"/>
<t:test_case testcaseid="Ping" type="always" >
 <t:objective>basic system check</t:objective>

	<t:test required="true">
	 <t:request>
	   <PingRequest xmlns="urn:zimbraAdmin"/>
	 </t:request>
	  <t:response>
		<t:select path="//admin:PingResponse"/>
	 </t:response>
	</t:test>

</t:test_case>


<t:test_case testcaseid="NU_ChangePasswordRequest_acct_setup1" type="always" >
    <t:objective>create test accounts</t:objective>
    <t:steps> 1. Login to admin
              2. Create an account
              3. Modify it and make it as admin account.
    </t:steps>

    <t:test required="true" >
        <t:request>
            <AuthRequest xmlns="urn:zimbraAdmin">
                <name>${admin.user}</name>
                <password>${admin.password}</password>
            </AuthRequest>
        </t:request>
        <t:response>
            <t:select path="//admin:AuthResponse/admin:authToken" set="authToken"/>
         </t:response>
    </t:test>

    <t:test id="create_acct1" required="true">
        <t:request>
            <CreateAccountRequest xmlns="urn:zimbraAdmin">
                <name>${test_account.name}</name>
                <password>${test_account.password}</password>
            </CreateAccountRequest>
        </t:request>
        <t:response>
            <t:select path="//admin:CreateAccountResponse/admin:account" attr="id"  set="test_account.id"/>
            <t:select path='//admin:CreateAccountResponse/admin:account/admin:a[@n="zimbraMailHost"]' set="test_acct.server"/>
        </t:response>
    </t:test>

    <t:test id = "modifyaccountrequest2a" required="true">
        <t:request>
            <ModifyAccountRequest xmlns = "urn:zimbraAdmin">
                <id>${test_account.id}</id>
                <a n = "zimbraIsAdminAccount">TRUE</a>
            </ModifyAccountRequest>
        </t:request>
        <t:response>
            <t:select path = "//admin:ModifyAccountResponse/admin:account"/>
        </t:response>
    </t:test>

</t:test_case>


<t:test_case testcaseid="NU_ChangePasswordRequest_acct_setup2" type="always" >
    <t:objective>create test accounts using admin role user</t:objective>

    <t:test required="true" >
        <t:request>
            <AuthRequest xmlns="urn:zimbraAdmin">
                <name>${test_account.name}</name>
                <password>${test_account.password}</password>
            </AuthRequest>
        </t:request>
        <t:response>
              <t:select path="//admin:AuthResponse/admin:authToken" set="authToken"/>
        </t:response>
    </t:test>

    <t:test id="create_acct1a" required="true" >
        <t:request>
            <CreateAccountRequest xmlns="urn:zimbraAdmin">
                <name>${test_account1.name}</name>
                <password>${test_account1.password}</password>
                <a n="zimbraPasswordMinAge">7</a>
            </CreateAccountRequest>
        </t:request>
        <t:response>
            <t:select path="//admin:CreateAccountResponse/admin:account" attr="id"  set="test_account1.id"/>
            <t:select path='//admin:CreateAccountResponse/admin:account/admin:a[@n="zimbraMailHost"]' set="test_acct1.server"/>
        </t:response>
    </t:test>

    <!-- Change the password modification time to before the min age (3 days vs. 7 days) 
	-->
    <t:test id="create_acct1" depends="create_acct1a" required="true">
        <t:request>
            <ModifyAccountRequest xmlns="urn:zimbraAdmin">
                <id>${test_account1.id}</id>
                <a n="zimbraPasswordModifiedTime">${GENTIME(-3d)}</a>
            </ModifyAccountRequest>
        </t:request>
        <t:response>
            <t:select path="//admin:ModifyAccountResponse"/>
        </t:response>
    </t:test>

    <t:test id="create_acct2a" required="true">
         <t:request>
             <CreateAccountRequest xmlns="urn:zimbraAdmin">
                 <name>${test_account2.name}</name>
                 <password>${test_account2.password}</password>
                 <a n="zimbraPasswordMinAge">7</a>
             </CreateAccountRequest>
        </t:request>
        <t:response>
            <t:select path="//admin:CreateAccountResponse/admin:account" attr="id"  set="test_account2.id"/>
            <t:select path='//admin:CreateAccountResponse/admin:account/admin:a[@n="zimbraMailHost"]' set="test_acct2.server"/>
        </t:response>
    </t:test>

    <t:test id="create_acct2" depends="create_acct2a" required="true">
        <t:request>
            <ModifyAccountRequest xmlns="urn:zimbraAdmin">
                <id>${test_account2.id}</id>
                <a n="zimbraPasswordModifiedTime">${GENTIME(-10d)}</a>
	    </ModifyAccountRequest>
        </t:request>
        <t:response>
            <t:select path="//admin:ModifyAccountResponse"/>
        </t:response>
    </t:test>

    <t:test id="create_acct3a" required="true">
        <t:request>
            <CreateAccountRequest xmlns="urn:zimbraAdmin">
                <name>${test_account3.name}</name>
                <password>${test_account3.password}</password>
                <a n="zimbraPasswordMinAge">7</a>
            </CreateAccountRequest>
        </t:request>
        <t:response>
             <t:select path="//admin:CreateAccountResponse/admin:account" attr="id"  set="test_account3.id"/>
             <t:select path='//admin:CreateAccountResponse/admin:account/admin:a[@n="zimbraMailHost"]' set="test_acct3.server"/>
        </t:response>
    </t:test>

    <t:test id="create_acct3" depends="create_acct3a" required="true">
        <t:request>
            <ModifyAccountRequest xmlns="urn:zimbraAdmin">
                <id>${test_account3.id}</id>
                <a n="zimbraPasswordModifiedTime">${GENTIME(-10d)}</a>
            </ModifyAccountRequest>
        </t:request>
        <t:response>
            <t:select path="//admin:ModifyAccountResponse"/>
        </t:response>
    </t:test>

    <t:test id="create_acct4a" required="true">
        <t:request>
            <CreateAccountRequest xmlns="urn:zimbraAdmin">
                <name>${test_account4.name}</name>
                <password>${test_account4.password}</password>
                <a n="zimbraPasswordMaxAge">60</a>
                <a n="zimbraPasswordMinAge">7</a>
            </CreateAccountRequest>
        </t:request>
        <t:response>
            <t:select path="//admin:CreateAccountResponse/admin:account" attr="id"  set="test_account4.id"/>
            <t:select path='//admin:CreateAccountResponse/admin:account/admin:a[@n="zimbraMailHost"]' set="test_acct4.server"/>
        </t:response>
    </t:test>

    <t:test id="create_acct4" depends="create_acct4a" required="true">
        <t:request>
            <ModifyAccountRequest xmlns="urn:zimbraAdmin">
                <id>${test_account4.id}</id>
                <a n="zimbraPasswordModifiedTime">${GENTIME(-61d)}</a>
             </ModifyAccountRequest>
         </t:request>
	 <t:response>
             <t:select path="//admin:ModifyAccountResponse"/>
         </t:response>
    </t:test>


    <t:test id="create_acct6a" required="true">
        <t:request>
            <CreateAccountRequest xmlns="urn:zimbraAdmin">
                <name>${test_account6.name}</name>
                <password>${test_account6.password}</password>
                <a n="zimbraPasswordMaxAge">0</a>
                <a n="zimbraPasswordMinAge">7</a>
            </CreateAccountRequest>
        </t:request>
        <t:response>
             <t:select path="//admin:CreateAccountResponse/admin:account" attr="id"  set="test_account6.id"/>
             <t:select path='//admin:CreateAccountResponse/admin:account/admin:a[@n="zimbraMailHost"]' set="test_acct6.server"/>
        </t:response>
    </t:test>

    <t:test id="create_acct6" depends="create_acct6a" required="true">
        <t:request>
            <ModifyAccountRequest xmlns="urn:zimbraAdmin">
                <id>${test_account6.id}</id>
                <a n="zimbraPasswordModifiedTime">${GENTIME(-1915d)}</a>
            </ModifyAccountRequest>
        </t:request>
	<t:response>
            <t:select path="//admin:ModifyAccountResponse"/>
        </t:response>
    </t:test>

	<!--
		Creation of test_account7, test_account8,
		test_account9, and test_account10 occurs below,
		to minimize the time between password
		modification and login
	-->

    <t:test id="create_acct11a" required="true">
        <t:request>
            <CreateAccountRequest xmlns="urn:zimbraAdmin">
                <name>${test_account11.name}</name>
                <password>${test_account11.password}</password>
                <a n="zimbraPasswordMaxAge">365</a>
                <a n="zimbraPasswordMinAge">7</a>
            </CreateAccountRequest>
        </t:request>
        <t:response>
             <t:select path="//admin:CreateAccountResponse/admin:account" attr="id"  set="test_account11.id"/>
             <t:select path='//admin:CreateAccountResponse/admin:account/admin:a[@n="zimbraMailHost"]' set="test_acct11.server"/>
        </t:response>
    </t:test>

    <t:test id="create_acct11" depends="create_acct11a" required="true">
        <t:request>
            <ModifyAccountRequest xmlns="urn:zimbraAdmin">
                <id>${test_account11.id}</id>
                <a n="zimbraPasswordModifiedTime">${GENTIME(-364d)}</a>
            </ModifyAccountRequest>
        </t:request>
        <t:response>
            <t:select path="//admin:ModifyAccountResponse"/>
        </t:response>
    </t:test>

    <t:test id="create_acct12a" required="true">
        <t:request>
            <CreateAccountRequest xmlns="urn:zimbraAdmin">
                <name>${test_account12.name}</name>
	        <password>${test_account12.password}</password>
                <a n="zimbraPasswordMaxAge">365</a>
                <a n="zimbraPasswordMinAge">7</a>
            </CreateAccountRequest>
        </t:request>
        <t:response>
            <t:select path="//admin:CreateAccountResponse/admin:account" attr="id"  set="test_account12.id"/>
            <t:select path='//admin:CreateAccountResponse/admin:account/admin:a[@n="zimbraMailHost"]' set="test_acct12.server"/>
        </t:response>
    </t:test>

    <t:test id="create_acct12" depends="create_acct12a" required="true">
        <t:request>
            <ModifyAccountRequest xmlns="urn:zimbraAdmin">
                <id>${test_account12.id}</id>
                <a n="zimbraPasswordModifiedTime">${GENTIME(-366d)}</a>
            </ModifyAccountRequest>
        </t:request>
	<t:response>
            <t:select path="//admin:ModifyAccountResponse"/>
         </t:response>
    </t:test>

</t:test_case>



<t:property name="server.zimbraAccount" value="${test_acct1.server}"/>
<t:test_case testcaseid="NU_ChangePasswordRequest_Age1" type="sanity">
    <t:objective> Verify that a user cannot change his password if it's age is not past the minimum </t:objective>

    <t:test id="NU_ChangePasswordRequest_Age1a" depends="create_acct1">
        <t:request>
            <AuthRequest xmlns="urn:zimbraAccount">
                <account by="name">${test_account1.name}</account>
                <password>${test_account1.password}</password>
	    </AuthRequest>
	 </t:request>
	 <t:response>
		<t:select path="//acct:AuthResponse/acct:lifetime"  match="^\d+$"/>
		<t:select path="//acct:AuthResponse/acct:authToken" set="authToken"/>

	 </t:response>
    </t:test>

    <t:test depends="NU_ChangePasswordRequest_Age1a">
        <t:request>
            <ChangePasswordRequest xmlns="urn:zimbraAccount">
                <account by="name">${test_account1.name}</account>
                <oldPassword>${test_account1.password}</oldPassword>
                <password>${test_account1.tmp_password}</password>
            </ChangePasswordRequest>
	 </t:request>
	 <t:response>
             <t:select path="//zimbra:Code"  match="^account.PASSWORD_CHANGE_TOO_SOON$"/>
	 </t:response>
	</t:test>

</t:test_case>

<t:property name="server.zimbraAccount" value="${test_acct2.server}"/>
<t:test_case testcaseid="NU_ChangePasswordRequest_Age2" type="sanity" bugids="36154" >
    <t:objective> Verify that after a user changes his password, that the timestamp is updated, and he cannot change the password again, since its age is not past the minimum.  </t:objective>

    <t:test id="NU_ChangePasswordRequest_Age2a" depends="create_acct2">
        <t:request>
            <AuthRequest xmlns="urn:zimbraAccount">
                <account by="name">${test_account2.name}</account>
                <password>${test_account2.password}</password>
            </AuthRequest>
        </t:request>
        <t:response>
            <t:select path="//acct:AuthResponse/acct:lifetime"  match="^\d+$"/>
            <t:select path="//acct:AuthResponse/acct:authToken" set="authToken"/>

        </t:response>
    </t:test>

    <t:test id="NU_ChangePasswordRequest_Age2b" depends="NU_ChangePasswordRequest_Age2a">
        <t:request>
            <ChangePasswordRequest xmlns="urn:zimbraAccount">
                 <account by="name">${test_account2.name}</account>
                 <oldPassword>${test_account2.password}</oldPassword>
                 <password>${test_account2.tmp_password}</password>
            </ChangePasswordRequest>
        </t:request>
        <t:response>
            <t:select path="//acct:ChangePasswordResponse"/>
        </t:response>
    </t:test>

    <t:test depends="NU_ChangePasswordRequest_Age2b">
        <t:request>
            <ChangePasswordRequest xmlns="urn:zimbraAccount">
                <account by="name">${test_account2.name}</account>
                <oldPassword>${test_account2.tmp_password}</oldPassword>
                <password>${test_account2.password}</password>
            </ChangePasswordRequest>
        </t:request>
        <t:response>
            <t:select path="//zimbra:Code"  match="^account.PASSWORD_CHANGE_TOO_SOON$"/>
        </t:response>
    </t:test>

</t:test_case>

<t:property name="server.zimbraAccount" value="${test_acct3.server}"/>
<t:test_case testcaseid="NU_ChangePasswordRequest_Age3" type="sanity">
    <t:objective> Verify that a user can change his password if it's age is past the minimum.  </t:objective>

    <t:test id="NU_ChangePasswordRequest_Age3a" depends="create_acct3">
        <t:request>
            <AuthRequest xmlns="urn:zimbraAccount">
                <account by="name">${test_account3.name}</account>
                <password>${test_account3.password}</password>
            </AuthRequest>
        </t:request>
        <t:response>
            <t:select path="//acct:AuthResponse/acct:lifetime"  match="^\d+$"/>
            <t:select path="//acct:AuthResponse/acct:authToken" set="authToken"/>

        </t:response>
    </t:test>

    <t:test depends="NU_ChangePasswordRequest_Age3a">
        <t:request>
            <ChangePasswordRequest xmlns="urn:zimbraAccount">
                <account by="name">${test_account3.name}</account>
                <oldPassword>${test_account3.password}</oldPassword>
                <password>${test_account3.tmp_password}</password>
            </ChangePasswordRequest>
        </t:request>
        <t:response>
            <t:select path="//acct:ChangePasswordResponse"/>
        </t:response>
    </t:test>

</t:test_case>

<t:property name="server.zimbraAccount" value="${test_acct4.server}"/>
<t:test_case testcaseid="NU_ChangePasswordRequest_Age4" type="sanity">
    <t:objective> Verify that a user must change his password if its age is past the maximum </t:objective>

    <t:test id="NU_ChangePasswordRequest_Age4a" depends="create_acct4">
        <t:request>
            <AuthRequest xmlns="urn:zimbraAccount">
                <account by="name">${test_account4.name}</account>
                <password>${test_account4.password}</password>
            </AuthRequest>
        </t:request>
        <t:response>
            <t:select path="//zimbra:Code"  match="^account.CHANGE_PASSWORD$"/>
        </t:response>
    </t:test>

    <t:test depends="NU_ChangePasswordRequest_Age4a">
        <t:request>
            <ChangePasswordRequest xmlns="urn:zimbraAccount">
                <account by="name">${test_account4.name}</account>
	        <oldPassword>${test_account4.password}</oldPassword>
                <password>${test_account4.tmp_password}</password>
            </ChangePasswordRequest>
        </t:request>
        <t:response>
            <t:select path="//acct:ChangePasswordResponse"/>
        </t:response>
    </t:test>

</t:test_case>


<t:test_case testcaseid="NU_ChangePasswordRequest_Age5" type="sanity">
    <t:objective> Verify that a user can change his password immediately, if the minimum is set to 0 </t:objective>
    <t:steps> 1. Create the account, set the Max/Min age to 60/0, Login as the account, change the password (success) </t:steps>


<t:property name="server.zimbraAdmin" value="${zimbraServer.name}"/>
    <t:test id="NU_ChangePasswordRequest_Age5a">
        <t:request>
            <AuthRequest xmlns="urn:zimbraAdmin">
                <name>${admin.user}</name>
                <password>${admin.password}</password>
            </AuthRequest>
        </t:request>
        <t:response>
            <t:select path="//admin:AuthResponse/admin:authToken" set="authToken"/>
        </t:response>
    </t:test>

    <t:test id="NU_ChangePasswordRequest_Age5b" depends="NU_ChangePasswordRequest_Age5a">
        <t:request>
            <CreateAccountRequest xmlns="urn:zimbraAdmin">
                <name>${test_account5.name}</name>
                <password>${test_account5.password}</password>
                <a n="zimbraPasswordMaxAge">60</a>
                <a n="zimbraPasswordMinAge">0</a>
             </CreateAccountRequest>
        </t:request>
        <t:response>
            <t:select path="//admin:CreateAccountResponse/admin:account" attr="id"  set="test_account5.id"/>
            <t:select path='//admin:CreateAccountResponse/admin:account/admin:a[@n="zimbraMailHost"]' set="test_acct5.server"/>
        </t:response>
    </t:test>

<t:property name="server.zimbraAccount" value="${test_acct5.server}"/>
    <t:test id="NU_ChangePasswordRequest_Age5c" depends="NU_ChangePasswordRequest_Age5b">
        <t:request>
            <AuthRequest xmlns="urn:zimbraAccount">
                <account by="name">${test_account5.name}</account>
                <password>${test_account5.password}</password>
            </AuthRequest>
        </t:request>
        <t:response>
            <t:select path="//acct:AuthResponse/acct:lifetime"  match="^\d+$"/>
            <t:select path="//acct:AuthResponse/acct:authToken" set="authToken"/>

        </t:response>
    </t:test>

    <t:test id="NU_ChangePasswordRequest_Age5d" depends="NU_ChangePasswordRequest_Age5c">
        <t:request>
            <ChangePasswordRequest xmlns="urn:zimbraAccount">
                <account by="name">${test_account5.name}</account>
                <oldPassword>${test_account5.password}</oldPassword>
                <password>${test_account5.tmp_password}</password>
            </ChangePasswordRequest>
        </t:request>
        <t:response>
            <t:select path="//acct:ChangePasswordResponse"/>
        </t:response>
    </t:test>

</t:test_case>

<t:property name="server.zimbraAccount" value="${test_acct6.server}"/>
<t:test_case testcaseid="NU_ChangePasswordRequest_Age6" type="sanity">
    <t:objective> Verify that a user does not have to change his password if the change time is large and the maximum is set to 0 </t:objective>

    <t:test depends="create_acct6">
        <t:request>
            <AuthRequest xmlns="urn:zimbraAccount">
                <account by="name">${test_account6.name}</account>
                <password>${test_account6.password}</password>
            </AuthRequest>
        </t:request>
        <t:response>
            <t:select path="//acct:AuthResponse/acct:lifetime"  match="^\d+$"/>
            <t:select path="//acct:AuthResponse/acct:authToken" set="authToken"/>

        </t:response>
     </t:test>

</t:test_case>


<t:test_case testcaseid="NU_ChangePasswordRequest_Age7" type="sanity">
    <t:objective> Verify that the granularity of the minimum password age is to the second </t:objective> 

    <t:steps> 1. Create account with Max/Min age = 60/1 2. Login as account 3. Change password (PASS_CHANGE_TOO_SOON) </t:steps>


<t:property name="server.zimbraAdmin" value="${zimbraServer.name}"/>
    <t:test id="NU_ChangePasswordRequest_Age7a">
        <t:request>
            <AuthRequest xmlns="urn:zimbraAdmin">
                <name>${admin.user}</name>
                <password>${admin.password}</password>
            </AuthRequest>
        </t:request>
        <t:response>
            <t:select path="//admin:AuthResponse/admin:authToken" set="authToken"/>
        </t:response>
    </t:test>

    <t:test id="NU_ChangePasswordRequest_Age7b" depends="NU_ChangePasswordRequest_Age7a">
        <t:request>
            <CreateAccountRequest xmlns="urn:zimbraAdmin">
                <name>${test_account7.name}</name>
                <password>${test_account7.password}</password>
                <a n="zimbraPasswordMaxAge">60</a>
                <a n="zimbraPasswordMinAge">1</a>
            </CreateAccountRequest>
	 </t:request>
	 <t:response>
		<t:select path="//admin:CreateAccountResponse/admin:account" attr="id"  set="test_account7.id"/>
              <t:select path='//admin:CreateAccountResponse/admin:account/admin:a[@n="zimbraMailHost"]' set="test_acct7.server"/>
	 </t:response>
    </t:test>

    <t:test id="NU_ChangePasswordRequest_Age7c" depends="NU_ChangePasswordRequest_Age7b">
        <t:request>
            <ModifyAccountRequest xmlns="urn:zimbraAdmin">
                <id>${test_account7.id}</id>
                <a n="zimbraPasswordModifiedTime">${GENTIME(-86370s)}</a>
            </ModifyAccountRequest>
        </t:request>
        <t:response>
            <t:select path="//admin:ModifyAccountResponse"/>
        </t:response>
    </t:test>

<t:property name="server.zimbraAccount" value="${test_acct7.server}"/>
    <t:test id="NU_ChangePasswordRequest_Age7d" depends="NU_ChangePasswordRequest_Age7c">
        <t:request>
            <AuthRequest xmlns="urn:zimbraAccount">
                <account by="name">${test_account7.name}</account>
                <password>${test_account7.password}</password>
            </AuthRequest>
        </t:request>
        <t:response>
            <t:select path="//acct:AuthResponse/acct:lifetime"  match="^\d+$"/>
            <t:select path="//acct:AuthResponse/acct:authToken" set="authToken"/>

        </t:response>
    </t:test>

    <t:test depends="NU_ChangePasswordRequest_Age7d">
        <t:request>
            <ChangePasswordRequest xmlns="urn:zimbraAccount">
                <account by="name">${test_account7.name}</account>
                <oldPassword>${test_account7.password}</oldPassword>
                <password>${test_account7.tmp_password}</password>
            </ChangePasswordRequest>
        </t:request>
        <t:response>
            <t:select path="//zimbra:Code"  match="^account.PASSWORD_CHANGE_TOO_SOON$"/>
         </t:response>
    </t:test>

</t:test_case>


<t:test_case testcaseid="NU_ChangePasswordRequest_Age8" type="sanity">
    <t:objective> TBD? </t:objective>

<t:property name="server.zimbraAdmin" value="${zimbraServer.name}"/>
    <t:test id="NU_ChangePasswordRequest_Age8a">
        <t:request>
            <AuthRequest xmlns="urn:zimbraAdmin">
                <name>${admin.user}</name>
                <password>${admin.password}</password>
            </AuthRequest>
         </t:request>
	 <t:response>
	    <t:select path="//admin:AuthResponse/admin:authToken" set="authToken"/>
	 </t:response>
    </t:test>

    <t:test id="NU_ChangePasswordRequest_Age8b" depends="NU_ChangePasswordRequest_Age8a">
        <t:request>
            <CreateAccountRequest xmlns="urn:zimbraAdmin">
                <name>${test_account8.name}</name>
                <password>${test_account8.password}</password>
                <a n="zimbraPasswordMaxAge">60</a>
                <a n="zimbraPasswordMinAge">1</a>
            </CreateAccountRequest>
        </t:request>
        <t:response>
            <t:select path="//admin:CreateAccountResponse/admin:account" attr="id"  set="test_account8.id"/>
            <t:select path='//admin:CreateAccountResponse/admin:account/admin:a[@n="zimbraMailHost"]' set="test_acct8.server"/>
        </t:response>
    </t:test>

    <t:test id="NU_ChangePasswordRequest_Age8c" depends="NU_ChangePasswordRequest_Age8b">
        <t:request>
            <ModifyAccountRequest xmlns="urn:zimbraAdmin">
                <id>${test_account8.id}</id>
                <a n="zimbraPasswordModifiedTime">${GENTIME(-86430s)}</a>
            </ModifyAccountRequest>
        </t:request>
        <t:response>
            <t:select path="//admin:ModifyAccountResponse"/>
        </t:response>
    </t:test>

<t:property name="server.zimbraAccount" value="${test_acct8.server}"/>
    <t:test id="NU_ChangePasswordRequest_Age8d" depends="NU_ChangePasswordRequest_Age8c">
        <t:request>
            <AuthRequest xmlns="urn:zimbraAccount">
                <account by="name">${test_account8.name}</account>
                <password>${test_account8.password}</password>
            </AuthRequest>
         </t:request>
         <t:response>
             <t:select path="//acct:AuthResponse/acct:lifetime"  match="^\d+$"/>
             <t:select path="//acct:AuthResponse/acct:authToken" set="authToken"/>

	 </t:response>
    </t:test>

    <t:test depends="NU_ChangePasswordRequest_Age8d">
        <t:request>
            <ChangePasswordRequest xmlns="urn:zimbraAccount">
                <account by="name">${test_account8.name}</account>
                <oldPassword>${test_account8.password}</oldPassword>
                <password>${test_account8.tmp_password}</password>
            </ChangePasswordRequest>
        </t:request>
        <t:response>
            <t:select path="//acct:ChangePasswordResponse"/>
        </t:response>
    </t:test>

</t:test_case>


<t:test_case testcaseid="NU_ChangePasswordRequest_Age9" type="sanity">
    <t:objective> Verify that the granularity of the maximum password age is to the second </t:objective>

<t:property name="server.zimbraAdmin" value="${zimbraServer.name}"/>
    <t:test id="NU_ChangePasswordRequest_Age9a">
        <t:request>
            <AuthRequest xmlns="urn:zimbraAdmin">
                <name>${admin.user}</name>
                <password>${admin.password}</password>
            </AuthRequest>
        </t:request>
        <t:response>
            <t:select path="//admin:AuthResponse/admin:authToken" set="authToken"/>
        </t:response>
    </t:test>

    <t:test id="NU_ChangePasswordRequest_Age9b" depends="NU_ChangePasswordRequest_Age9a">
        <t:request>
            <CreateAccountRequest xmlns="urn:zimbraAdmin">
                <name>${test_account9.name}</name>
                <password>${test_account9.password}</password>
                <a n="zimbraPasswordMaxAge">1</a>
                <a n="zimbraPasswordMinAge">0</a>
            </CreateAccountRequest>
	 </t:request>
	 <t:response>
		<t:select path="//admin:CreateAccountResponse/admin:account" attr="id"  set="test_account9.id"/>
              <t:select path='//admin:CreateAccountResponse/admin:account/admin:a[@n="zimbraMailHost"]' set="test_acct9.server"/>
	 </t:response>
    </t:test>

    <t:test id="NU_ChangePasswordRequest_Age9c" depends="NU_ChangePasswordRequest_Age9b">
        <t:request>
            <ModifyAccountRequest xmlns="urn:zimbraAdmin">
                <id>${test_account9.id}</id>
                <a n="zimbraPasswordModifiedTime">${GENTIME(-86350s)}</a>
            </ModifyAccountRequest>
        </t:request>
        <t:response>
            <t:select path="//admin:ModifyAccountResponse"/>
        </t:response>
    </t:test>

<t:property name="server.zimbraAccount" value="${test_acct9.server}"/>
    <t:test depends="NU_ChangePasswordRequest_Age9c">
        <t:request>
            <AuthRequest xmlns="urn:zimbraAccount">
               <account by="name">${test_account9.name}</account>
               <password>${test_account9.password}</password>
            </AuthRequest>
	 </t:request>
	 <t:response>
		<t:select path="//acct:AuthResponse/acct:lifetime"  match="^\d+$"/>
		<t:select path="//acct:AuthResponse/acct:authToken" set="authToken"/>

	 </t:response>
    </t:test>

</t:test_case>


<t:test_case testcaseid="NU_ChangePasswordRequest_Age10" type="sanity">
	<t:objective> TBD? </t:objective>

<t:property name="server.zimbraAdmin" value="${zimbraServer.name}"/>

	<t:test id="NU_ChangePasswordRequest_Age10a" >
	 <t:request>
	  <AuthRequest xmlns="urn:zimbraAdmin">
	    <name>${admin.user}</name>
	    <password>${admin.password}</password>
	  </AuthRequest>
	 </t:request>
	 <t:response>
	    <t:select path="//admin:AuthResponse/admin:authToken" set="authToken"/>
	 </t:response>
	</t:test>

	<t:test id="NU_ChangePasswordRequest_Age10b" depends="NU_ChangePasswordRequest_Age10a" >
	 <t:request>
	  <CreateAccountRequest xmlns="urn:zimbraAdmin">
	    <name>${test_account10.name}</name>
	    <password>${test_account10.password}</password>
	    <a n="zimbraPasswordMaxAge">1</a>
	    <a n="zimbraPasswordMinAge">0</a>
	  </CreateAccountRequest>
	 </t:request>
	 <t:response>
		<t:select path="//admin:CreateAccountResponse/admin:account" attr="id"  set="test_account10.id"/>
              <t:select path='//admin:CreateAccountResponse/admin:account/admin:a[@n="zimbraMailHost"]' set="test_acct10.server"/>
	 </t:response>
	</t:test>

	<t:test id="NU_ChangePasswordRequest_Age10c" depends="NU_ChangePasswordRequest_Age10b" >
	 <t:request>
	  <ModifyAccountRequest xmlns="urn:zimbraAdmin">
	    <id>${test_account10.id}</id>
	    <a n="zimbraPasswordModifiedTime">${GENTIME(-86401s)}</a>
	  </ModifyAccountRequest>
	 </t:request>
	 <t:response>
		<t:select path="//admin:ModifyAccountResponse"/>
	 </t:response>
	</t:test>

<t:property name="server.zimbraAccount" value="${test_acct10.server}"/>
	<t:test depends="NU_ChangePasswordRequest_Age10c" >
	 <t:request>
	  <AuthRequest xmlns="urn:zimbraAccount">
	    <account by="name">${test_account10.name}</account>
	    <password>${test_account10.password}</password>
	    <!--<prefs/>-->
	  </AuthRequest>
	 </t:request>
	 <t:response>
		<t:select path="//zimbra:Code"  match="^account.CHANGE_PASSWORD$"/>
	 </t:response>
	</t:test>

</t:test_case>

<t:property name="server.zimbraAccount" value="${test_acct11.server}"/>
<t:test_case testcaseid="NU_ChangePasswordRequest_Age11" type="sanity">
    <t:objective> Verify that the granularity of the maximum password age is to the year </t:objective>

    <t:test id="NU_ChangePasswordRequest_Age11a" depends="create_acct6">
	 <t:request>
	  <AuthRequest xmlns="urn:zimbraAccount">
	    <account by="name">${test_account11.name}</account>
	    <password>${test_account11.password}</password>
	    <!--<prefs/>-->
	  </AuthRequest>
	 </t:request>
	 <t:response>
		<t:select path="//acct:AuthResponse/acct:lifetime"  match="^\d+$"/>
		<t:select path="//acct:AuthResponse/acct:authToken" set="authToken"/>

	 </t:response>
	</t:test>

</t:test_case>

<t:property name="server.zimbraAccount" value="${test_acct12.server}"/>
<t:test_case testcaseid="NU_ChangePasswordRequest_Age12" type="sanity">
	<t:objective> TBD? </t:objective>

	<t:test depends="create_acct12">
	 <t:request>
	  <AuthRequest xmlns="urn:zimbraAccount">
	    <account by="name">${test_account12.name}</account>
	    <password>${test_account12.password}</password>
	  </AuthRequest>
	 </t:request>
	 <t:response>
		<t:select path="//zimbra:Code"  match="^account.CHANGE_PASSWORD$"/>
	 </t:response>
	</t:test>

</t:test_case>


</t:tests>

