<t:tests xmlns:t="urn:zimbraTestHarness">

<t:property name="account1.name" value="account1.${TIME}.${COUNTER}@${defaultdomain.name}"/>
<t:property name="account2.name" value="account2.${TIME}.${COUNTER}@${defaultdomain.name}"/>

<t:property name="account1.JPGfile1" value="${testMailRaw.root}/bug60053/Sunset.jpg"/>
<t:property name="account1.JPGfile2" value="${testMailRaw.root}/bug60053/IMG_7120.JPG"/>

<t:property name="grant.usr"		value="usr"/>
<t:property name="op.grant"			value="grant"/>

<t:test_case testcaseid="ViewImages_60053_Setup" type="always" >
    <t:objective>Test set up</t:objective>

	<t:property name="server.zimbraAdmin" value="${zimbraServer.name}"/>	
    <t:test id="ping" required="true">
        <t:request>
            <PingRequest xmlns="urn:zimbraAdmin"/>
        </t:request>
        <t:response>
            <t:select path="//admin:PingResponse"/>
        </t:response>
    </t:test>

    <t:test  >
        <t:request>
            <AuthRequest xmlns="urn:zimbraAdmin">
                <name>${admin.user}</name>
                <password>${admin.password}</password>
            </AuthRequest>
        </t:request>
        <t:response>
            <t:select path="//admin:AuthResponse/admin:authToken" set="authToken"/>
        </t:response>
    </t:test>

    <t:test >
        <t:request>
            <CreateAccountRequest xmlns="urn:zimbraAdmin">
                <name>${account1.name}</name>
                <password>${defaultpassword.value}</password>
            </CreateAccountRequest>
        </t:request>
        <t:response>
            <t:select path="//admin:CreateAccountResponse/admin:account" attr="id"  set="account1.id"/>
			<t:select path='//admin:CreateAccountResponse/admin:account/admin:a[@n="zimbraMailHost"]' set="account1.server"/>
        </t:response>
    </t:test>  
    
    <t:test >
        <t:request>
            <CreateAccountRequest xmlns="urn:zimbraAdmin">
                <name>${account2.name}</name>
                <password>${defaultpassword.value}</password>
            </CreateAccountRequest>
        </t:request>
        <t:response>
            <t:select path="//admin:CreateAccountResponse/admin:account" attr="id"  set="account2.id"/>
			<t:select path='//admin:CreateAccountResponse/admin:account/admin:a[@n="zimbraMailHost"]' set="account2.server"/>
        </t:response>
    </t:test>  

	<t:property name="server.zimbraAccount" value="${account1.server}"/>


</t:test_case>


<t:test_case testcaseid="ViewAllImages_01" type="smoke" bugids="60053" >
    <t:objective>Send multiple pictures as attachment and verify the attachment </t:objective>
    
    <t:steps>
	    1. Login to account1
	    2. Upload a two pictures in the briefcase folder
	    3. Attach those picture and send email to account 2	   
	    4. Verify the sent message and the attachment
    </t:steps>

	<t:property name="server.zimbraAccount" value="${account1.server}"/>

    <t:test >
        <t:request>
            <AuthRequest xmlns="urn:zimbraAccount">
                <account by="name">${account1.name}</account>
                <password>${defaultpassword.value}</password>
            </AuthRequest>
        </t:request>
        <t:response>
            <t:select path="//acct:AuthResponse/acct:authToken" set="authToken"/>
        </t:response>
    </t:test>

	<t:test>
		<t:request>
			<GetFolderRequest xmlns="urn:zimbraMail"/>
		</t:request>
		<t:response>
			<t:select path="//mail:GetFolderResponse/mail:folder/mail:folder[@name='${globals.briefcase}']" attr="id" set="account1.folder.briefcase.id"/>
		</t:response>
	</t:test>
	
	<t:uploadservlettest>
		<t:uploadServletRequest>
			<filename>${account1.JPGfile1}</filename>
		</t:uploadServletRequest>
		<t:uploadServletResponse>
			<t:select attr="id" set="document.upload1.id"/>
		</t:uploadServletResponse>
	</t:uploadservlettest>
	
	<t:test >
        <t:request>
			<SaveDocumentRequest xmlns="urn:zimbraMail">
			  <doc l="${account1.folder.briefcase.id}">
			    <upload id="${document.upload1.id}"/>
			  </doc>
			</SaveDocumentRequest>
        </t:request>
        <t:response>
            <t:select path="//mail:SaveDocumentResponse/mail:doc" attr="id" set="document1.attachfile.id"/>
        </t:response>
    </t:test>
	
	<t:uploadservlettest>
		<t:uploadServletRequest>
			<filename>${account1.JPGfile2}</filename>
		</t:uploadServletRequest>
		<t:uploadServletResponse>
			<t:select attr="id" set="document.upload2.id"/>
		</t:uploadServletResponse>
	</t:uploadservlettest>	     
	     
	<t:test >
        <t:request>
			<SaveDocumentRequest xmlns="urn:zimbraMail">
			  <doc l="${account1.folder.briefcase.id}">
			    <upload id="${document.upload2.id}"/>
			  </doc>
			</SaveDocumentRequest>
        </t:request>
        <t:response>
            <t:select path="//mail:SaveDocumentResponse/mail:doc" attr="id" set="document2.attachfile.id"/>
        </t:response>
    </t:test>
	
    <t:test >
        <t:request>
			<SaveDraftRequest xmlns="urn:zimbraMail">
			 <m> 			 
			    <attach>
			    <doc id="${document1.attachfile.id}" />
			    <doc id="${document2.attachfile.id}" />
			    </attach>
			    
			    <e t="f" a='${account1.name}'/>
			  </m>
			</SaveDraftRequest>
        </t:request>
        <t:response>
            <t:select path="//mail:SaveDraftResponse/mail:m" attr="id" set="account1.attach1.id"/>
        </t:response>
    </t:test>    
    
	<t:test >
		<t:request>
			<SendMsgRequest xmlns="urn:zimbraMail">			
				<m >
					<e t="t" a='${account2.name}'/>
					<su> "Send with attachment" </su>									 			
					 <attach>
							<mp mid="${account1.attach1.id}" part="1" />
							<mp mid="${account1.attach1.id}" part="2" />								
					</attach>				   		
				</m>
			</SendMsgRequest>
		</t:request>
		<t:response>
			<t:select path="//mail:SendMsgResponse/mail:m" attr="id" set="sentmsg1.id"/>
		</t:response>
	</t:test>
	
	<t:test>
		<t:request>
			<GetMsgRequest xmlns="urn:zimbraMail">
				<m id="${sentmsg1.id}" read="1" />
			</GetMsgRequest>
		</t:request>
		<t:response>
			<t:select path="//mail:GetMsgResponse/mail:m" attr="id" match="${sentmsg1.id}"/>
		</t:response>
	</t:test>	
	
	<t:test >
        <t:request>
            <AuthRequest xmlns="urn:zimbraAccount">
                <account by="name">${account2.name}</account>
                <password>${defaultpassword.value}</password>
            </AuthRequest>
        </t:request>
        <t:response>
            <t:select path="//acct:AuthResponse/acct:authToken" set="authToken"/>
        </t:response>
    </t:test>
	
	<t:resttest>
		<t:restServletRequest>
			<basepath>/h/viewimages</basepath>			
			<id>${document1.attachfile.id}</id>		
		</t:restServletRequest>
		<t:restServletResponse>
			<t:select attr="StatusCode" match="200"/>
		</t:restServletResponse>
	</t:resttest>
	
</t:test_case>


</t:tests>

